stimfileapi/__init__.py
stimfileapi/__main__.py
stimfileapi/download.py
stimfileapi/hash.py
stimfileapi/proto/fileapi_grpc.py
stimfileapi/proto/fileapi_pb2.py
stimfileapi/upload.py
stimfileapi/usage.py
stimfileapi-0.1.3.dist-info/LICENSE
stimfileapi-0.1.3.dist-info/METADATA
stimfileapi-0.1.3.dist-info/WHEEL
stimfileapi-0.1.3.dist-info/entry_points.txt
stimfileapi-0.1.3.dist-info/RECORD
