Metadata-Version: 2.3
Name: stimfileapi
Version: 0.1.3
Summary: StealthIM FileAPI Upload/Download Command Toolkit
License: GPLv2
Author: cxykevin
Author-email: cxykevin@yeah.net
Requires-Python: >=3.13
Classifier: License :: Other/Proprietary License
Classifier: Programming Language :: Python :: 3
Classifier: Programming Language :: Python :: 3.13
Requires-Dist: aiofiles (>=24.1.0,<25.0.0)
Requires-Dist: blake3 (>=1.0.4,<2.0.0)
Requires-Dist: grpclib (>=0.4.7,<0.5.0)
Requires-Dist: protobuf (>=6.30.2,<7.0.0)
Requires-Dist: typer (>=0.15.2,<0.16.0)
